{
  "video_id": "0e9yctlsFWo",
  "comment_count": 4,
  "comments": [
    {
      "author": "@tacoburrito1503",
      "text": "갑자기 비닐봉지 바스락거리는 소리나길래 내껀줄 ㅋㅋㅋ 22:00",
      "likeCount": 0,
      "publishedAt": "2017-03-14T12:09:05Z"
    },
    {
      "author": "@고양이-k4z",
      "text": "19:34",
      "likeCount": 0,
      "publishedAt": "2019-06-06T08:04:14Z"
    },
    {
      "author": "@kael9694",
      "text": "코어전설주세요 : 와우\n착맨 : 히오스합시다!? 네",
      "likeCount": 0,
      "publishedAt": "2017-03-14T11:13:14Z"
    },
    {
      "author": "@김경민-p4l",
      "text": "불법강사 침착맨",
      "likeCount": 0,
      "publishedAt": "2017-03-14T14:29:44Z"
    }
  ]
}