{
  "video_id": "6g4OAEhF-cY",
  "comment_count": 8,
  "comments": [
    {
      "author": "@ckrus23",
      "text": "7:25 일침맨\n15:28 17:15 18:34 공명전을 보기 위해 몰려드는 사람들과 그 반응\n27:25 야 카라짐 너 특성 뭐 찍었냐\n28:50 똥스똥톤 vs 킹갓전",
      "likeCount": 1,
      "publishedAt": "2020-01-22T05:13:52Z"
    },
    {
      "author": "@pepperchili728",
      "text": "0:34 찰지구나 그리고 더 대장같은 남만병과 두번째 칠종칠금\n2:50 맹획의 계략\n7:13 제갈량 위에 있는 침갈량 노수 출진\n11:41 마왕이 온다\n14:11 제갈량과 맹획의 수 싸움\n18:08 조운 vs 대래\n27:51 세번째 칠종칠금 제갈량 공명전 10승 3무\n29:34 제2장 남정편 3막 남만 싸움",
      "likeCount": 0,
      "publishedAt": "2025-03-26T02:07:38Z"
    },
    {
      "author": "@uchirachi",
      "text": "공명전에서 관흥은 생각 외로 종잇장이라 회복의보리 여러개 갖고 다니면서 신경써줘야 합니다",
      "likeCount": 0,
      "publishedAt": "2021-12-27T03:58:04Z"
    },
    {
      "author": "@런우",
      "text": "29:43 무기상입니다만?",
      "likeCount": 0,
      "publishedAt": "2023-04-10T09:48:05Z"
    },
    {
      "author": "@tesargo7532",
      "text": "호스팅타고온 트수들 반응이 너무웃기네요 ㅋㅋㅋㅋㅋ",
      "likeCount": 0,
      "publishedAt": "2019-07-13T15:55:52Z"
    },
    {
      "author": "@power5422",
      "text": "조조전은 안하나여?",
      "likeCount": 0,
      "publishedAt": "2016-12-03T13:00:06Z"
    },
    {
      "author": "@레콘맨",
      "text": "장억님 축지법 쓰신다",
      "likeCount": 0,
      "publishedAt": "2019-05-11T13:11:01Z"
    },
    {
      "author": "@kellogg9822",
      "text": "왜 클릭할때마다 suv 소리나지",
      "likeCount": 0,
      "publishedAt": "2018-11-18T03:30:13Z"
    }
  ]
}