{
  "video_id": "o5_ITo4lRQY",
  "comment_count": 100,
  "comments": [
    {
      "author": "@chamjimaseeon",
      "text": "잘때 들으면서 자려고 키면 잠은 무슨 낄낄거리다가 잠 못잠ㅋㅋㅋㅋㅋㅋㅋㅋㅋㅋㅋㅋ",
      "likeCount": 2526,
      "publishedAt": "2020-02-29T18:04:22Z"
    },
    {
      "author": "@릴리-o5c",
      "text": "이렇게 재밌는걸 이제야…침착맨 오마카세야 감사하다~",
      "likeCount": 779,
      "publishedAt": "2022-12-01T15:50:22Z"
    },
    {
      "author": "@쿄마",
      "text": "모래마찰 도네한사람 존나웃기네 진짜 ㅋㅋㅋㅋㅋㅋㅋ",
      "likeCount": 2618,
      "publishedAt": "2020-02-28T11:06:30Z"
    },
    {
      "author": "@yunseonggim7893",
      "text": "오늘을 위해 설거지 1주일치 모아뒀다ㅋㅋㅋ\n엄마한테 나 뒤졌다ㅋㅋㅋ",
      "likeCount": 2632,
      "publishedAt": "2020-02-28T10:23:13Z"
    },
    {
      "author": "@nyangurae1354",
      "text": "16강 월드컵이지만 월드컵 속 월드컵이라 무한으로 즐길수 있는 월드컵... 이건 귀하군요...",
      "likeCount": 1612,
      "publishedAt": "2020-02-28T10:02:48Z"
    },
    {
      "author": "@모레츠-m4z",
      "text": "이번 편에서 침착맨 심성이 진짜 선한게 드러났는데 씽크대 깨끗해지라고 콜라 뿌리는 것도 모자라서 날파리 죽이기 싫다고 콜라로 목욕시켜주는거에 너무 감동받았다",
      "likeCount": 115,
      "publishedAt": "2020-02-29T05:18:56Z"
    },
    {
      "author": "@2_kw-v9y",
      "text": "이시국에 자가격리를 돕는 침투부 월드컵이 어쩌면 최고의 백신일지도...?",
      "likeCount": 1405,
      "publishedAt": "2020-02-28T10:56:01Z"
    },
    {
      "author": "@15gg13",
      "text": "42:05 인트로 모래마찰좌",
      "likeCount": 1425,
      "publishedAt": "2020-02-28T10:05:05Z"
    },
    {
      "author": "@dolbae99돌배",
      "text": "침튜부 보면서 느낀 침소리 발동코드\n\n1. 저는 이렇게 생각했어요\n2. 어? 이건 어때요?\n3. 그 뭐냐",
      "likeCount": 1114,
      "publishedAt": "2020-02-28T10:26:45Z"
    },
    {
      "author": "@황준준-o4m",
      "text": "인트로부터 빵터지네ㅋㅋㅋㄱㅋ",
      "likeCount": 256,
      "publishedAt": "2020-02-28T10:03:11Z"
    },
    {
      "author": "@장재미슴327",
      "text": "침조씨의 월드컵은 밥먹으면서 보기엔 함정이 너무 많다..\n여장한 직박이형과 팔짱데이트..\n바닥에 똥 분지르기..\n무릎똥...",
      "likeCount": 50,
      "publishedAt": "2020-02-29T01:32:28Z"
    },
    {
      "author": "@dean-d1r1o",
      "text": "은근히 사진 첨부 되는거 개웃김ㅋㅋㅋㅋ",
      "likeCount": 259,
      "publishedAt": "2020-02-28T10:16:10Z"
    },
    {
      "author": "@miraak6220",
      "text": "이번 월드컵 레전드로 웃기네 ㅋㅋㅋㅋㅋ bbq 4,5000원, 무릎똥, 모래마찰 등등 웃음포인트 개많아 ㅋㅋㅋㅋ",
      "likeCount": 18,
      "publishedAt": "2020-02-28T16:08:01Z"
    },
    {
      "author": "@우냐-x2b",
      "text": "이때는 bbq가 2배 해도 4만원이였네 세상에나",
      "likeCount": 5,
      "publishedAt": "2024-03-14T03:16:51Z"
    },
    {
      "author": "@BBAMHN",
      "text": "침착맨을 영원히 누릴 수 있는 시대에 살아서 좋다",
      "likeCount": 4,
      "publishedAt": "2025-09-06T17:45:32Z"
    },
    {
      "author": "@nam14526",
      "text": "27:56 경매시작\n30:00 더러운얘기시작\n42:05 모래마찰",
      "likeCount": 352,
      "publishedAt": "2020-02-28T12:51:22Z"
    },
    {
      "author": "@구글링-x9b",
      "text": "내가 무슨 부귀영화를 누리려고 밥먹을때 봐야겠다 했을까.",
      "likeCount": 52,
      "publishedAt": "2020-02-28T11:51:28Z"
    },
    {
      "author": "@닉넴결정장애",
      "text": "트수들 이날 컨디션 좋았네ㅋㅋ \n드립마다 빵빵터지네ㅋㅋㅋㅋㅋㅋㅋ",
      "likeCount": 64,
      "publishedAt": "2020-02-28T12:44:24Z"
    },
    {
      "author": "@swh5618",
      "text": "29:58 오줌맺히는 침착맨. \"나만 맺혀?\" 시전ㅋㅋ",
      "likeCount": 196,
      "publishedAt": "2020-02-28T11:50:28Z"
    },
    {
      "author": "@Daniel_Dcz",
      "text": "9:39\n???: 죽이기 싫은데.. 콜라 부어야겠다",
      "likeCount": 217,
      "publishedAt": "2020-02-28T10:37:39Z"
    },
    {
      "author": "@deartaks",
      "text": "그게 없네. 딱한번 아무도 모르게 똥먹기 vs 똥먹었다고 온세상에 오해받기",
      "likeCount": 64,
      "publishedAt": "2020-02-29T22:22:29Z"
    },
    {
      "author": "@병건83",
      "text": "32:45무릎똥 레전드 ㅋㅋㅋㅋㅋㅅㅋㅅㅋㅅㅋㅅㅋㅅㅋㅅㅋㅅㅋㅅㅋㅅㅋㅅㅋㅅㅋㅅㅋㅅㅋㅅㅋㅅㅋㅅㅋㅅㅋㅅㅋㅅㅋㅅㅋㅅㅋㅅㅋㅅㅋㅅㅋㅅㅋㅅㅋㅅㅋㅅㅋㅅㅋㅅㅋㅅㅋㅅㅋㅅㅋㅅㅋㅅㅋㅅㅋㅅㅋㅅㅋㅅㅋㅅㅋㅅㅋㅅㅋㅅㅋㅅㅋㅅㅋㅅㅋㅅㅋㅅㅋㅅㅋㅅㅋㅅㅋㅅㅋㅅㅋㅅㅋㅅㅋㅅㅋㅅㅋㅅㅋㅅㅋㅅㅋㅅㅋㅅㅋㅅㅋㅅㅋㅅㅋㅅㅋㅅㅋㅅㅋㅅㅋㅅㅋㅅㅋㅅㅋㅅㅋㅅㅋㅅㅋㅅㅋㅅㅋㅅㅋㅅㅋㅅㅋㅅㅋㅅㅋㅅㅋㅅㅋㅅㅋㅅㅋㅅㅋㅅㅋㅅㅋㅅㅋㅅㅋㅅㅋㅅㅋㅅㅋㅅㅋㅅㅋㅅㅋㅅㅋㅅㅋㅅㅋㅅㅋㅅㅋㅅㅋㅅㅋㅅㅋㅅㅋ",
      "likeCount": 91,
      "publishedAt": "2020-02-28T16:16:20Z"
    },
    {
      "author": "@tvoktop2490",
      "text": "02:47 자료화면 킹받네",
      "likeCount": 122,
      "publishedAt": "2020-02-28T10:04:56Z"
    },
    {
      "author": "@YK-zt9bb",
      "text": "ㅋㅋㅋㅋㅋㅋㅋㅋ일하면서 보다 웃음참기 챌린지했네 ㅋㅋㅋㅋㅋㅋㅋㅋ내 기준 지금까지 월드컵중에 웃긴 편으로 1등이다 진짴ㅋㅋㅋㅋㅋㅋㅋㅋㅋㅋㅋㅋ",
      "likeCount": 9,
      "publishedAt": "2020-02-29T03:10:49Z"
    },
    {
      "author": "@Caffeine_holic",
      "text": "진짜 죽을거 처럼 웃었네 ㅋㅋㄲㄱㅋㅋㅋㅋㅋㅋㄱㅋㄲㅋㅋㅋㄱㅋㄱㄲㅋㅋㄱㅋㄱ ㅋㄱㄱㄱㅋㄲㄱㅋㅋㄲㅋㄱㄱㅋㅋㅋㅋㄱㄱ",
      "likeCount": 76,
      "publishedAt": "2020-02-28T10:50:18Z"
    },
    {
      "author": "@준-z5c4y",
      "text": "침마카세 딱히 안보는데 알고리즘이 침착맨에 절여져서 옛날영상 계속뜸",
      "likeCount": 59,
      "publishedAt": "2022-12-03T10:17:07Z"
    },
    {
      "author": "@태안-m6d",
      "text": "32:26 댓글창에서 손에싸고 몸에 문지르면 된댘ㅋㅋㅋㅋ아 미쳤낰ㅋㅋㅋㅋㅋㅋㅋㅋㅋㅋㅋㅋㅋㅋㅋㅋㅋㅋㅋㅋㅋㅋㅋㅋㅋㅋㅋㅋㅋㅋ",
      "likeCount": 146,
      "publishedAt": "2020-02-28T17:39:38Z"
    },
    {
      "author": "@기영이와땡구",
      "text": "카타르 월드컵은 16강에서 멈췄지만\n침투부 월드컵은 연중무휴로 진행된다",
      "likeCount": 122,
      "publishedAt": "2022-12-07T15:04:39Z"
    },
    {
      "author": "@ukikaze9930",
      "text": "6:15 이건 침맨말이 맞지. 악취 못 맡는건 이득이 아니라 패널티임.  악취 못 맡으면 상한음식도 잘못먹을 수 있고  음식물쓰레기도 덜 자주 버릴거고  아무래도 청소도 덜 하게 되니 위생적으로 문제도 생김. 절대 좋은게 아니지",
      "likeCount": 4,
      "publishedAt": "2020-07-13T06:59:26Z"
    },
    {
      "author": "@Kkomong",
      "text": "이 영상보면서 잔뜩 쌓인 설거지 찢엇습니다.감사합니다 침착맨님",
      "likeCount": 10,
      "publishedAt": "2021-10-22T08:56:02Z"
    },
    {
      "author": "@이현민-h5v",
      "text": "침착맨: \n시청자: ㅇㅈ, ㄹㅇ, ㅇㅇ, 아 그거 기억나지, ㅋㅋㅋ",
      "likeCount": 18,
      "publishedAt": "2020-02-28T18:16:41Z"
    },
    {
      "author": "@박준수-e5s",
      "text": "오늘거는 트수들이랑 케미도 좋네ㅋㅋㅋㅋㅋㅋㅋㅋㅋㅋㅋ",
      "likeCount": 10,
      "publishedAt": "2020-02-28T12:50:39Z"
    },
    {
      "author": "@Eres_Tu",
      "text": "6:51 포상도 못 맡음 채팅 레전드",
      "likeCount": 8,
      "publishedAt": "2020-03-01T07:36:25Z"
    },
    {
      "author": "@그루미-f5e",
      "text": "19:58 청소는 엄마가 해줌 ㅇㅈㄹ ㅋㅋㅋㅋㅋㅋㅋㅋㅋㅋㅋㅋㅋㅋㅋㅋㅋㅋㅋㅋㅋ",
      "likeCount": 147,
      "publishedAt": "2020-02-28T10:56:21Z"
    },
    {
      "author": "@pheliznabidad",
      "text": "31:35 잔뜩< 이라고 표현한게 존나 웃김 ㅅㅂㅋㅋㅋㅋㅋㅋㅋㅋㅋㅋㅋ\n31:53 그리고 미친똥착맨 엉덩이 벌려서 바닥에 묻히래; 손으로 엉덩이 벌리는 모션 시댕ㅋㅋㅋㅋㅋㅋㅋㅋㅋ",
      "likeCount": 77,
      "publishedAt": "2020-02-28T15:25:14Z"
    },
    {
      "author": "@geon0813",
      "text": "원래 '내 방에서 어디로든 순간이동 vs 어디서든 내 방으로 순간이동' 이거 아님??",
      "likeCount": 8,
      "publishedAt": "2020-02-28T17:35:59Z"
    },
    {
      "author": "@callee2173",
      "text": "침맨의 월동으로 인해 여기까지 오다니..",
      "likeCount": 3,
      "publishedAt": "2023-10-25T13:07:27Z"
    },
    {
      "author": "@mj4kng",
      "text": "10:25 벌써 예견했구나 방장...",
      "likeCount": 5,
      "publishedAt": "2022-12-15T14:14:16Z"
    },
    {
      "author": "@LollipopCrush",
      "text": "오늘 ㅈㄴ더워서 보러왔습니다. 겨울 빨리와라",
      "likeCount": 1,
      "publishedAt": "2025-07-08T07:52:36Z"
    },
    {
      "author": "@okdongjiwoo",
      "text": "오늘따라 붉은 방장,,,어찌하여 고나우가 되어 오셨소 침공,,,",
      "likeCount": 16,
      "publishedAt": "2020-02-28T10:08:02Z"
    },
    {
      "author": "@fanclamdownman573",
      "text": "ㅋㅋㅋㅋ와...ㄹㅇ이번 월드컵 방장님 텐션 레게노ㅋㅋㅋㅋㅋㅋ쥰네 시간 가는줄모르고 웃었네",
      "likeCount": 7,
      "publishedAt": "2020-02-28T17:32:43Z"
    },
    {
      "author": "@whwlsgh1010",
      "text": "18:50 천재냨ㅋㅋ\n28:10 급 경매\n31:33 디테일 뭐냐고 ㅋㅋㅋㅋ\n42:00 썸넬",
      "likeCount": 5,
      "publishedAt": "2020-02-28T13:09:04Z"
    },
    {
      "author": "@MicroBoy21",
      "text": "진짜 무릎똥 얘기듣고 침흘리면서 웃었다 ㅋㅋㅋㅋㅋㅋㅋㅋㅋㅋㅋ",
      "likeCount": 36,
      "publishedAt": "2020-02-28T14:44:09Z"
    },
    {
      "author": "@홍준기-m9p",
      "text": "02:12 직박이형 소환ㅋㅋㅋㅋㅋ",
      "likeCount": 35,
      "publishedAt": "2020-02-28T10:27:57Z"
    },
    {
      "author": "@BerserkerJesus",
      "text": "원하는 곳 순간이동 vs 집으로 순간이동은 황금벨런스가 아닌듯... 원하는 곳 순간이동이 무조건 낫죠. 집앞으로 순간이동, 집앞 편의점으로 순간이동 하면 되는데",
      "likeCount": 2,
      "publishedAt": "2021-08-08T06:22:29Z"
    },
    {
      "author": "@깨달음-y5w",
      "text": "오늘 할일 빨리 끝내고 오랜만에 게임도하고\n치킨도 먹고 잘 놀다가 유튜브를 켜니\n침튜브 월드컵이있네? 와 이게 행복인가?",
      "likeCount": 2,
      "publishedAt": "2020-02-28T15:06:03Z"
    },
    {
      "author": "@s0op",
      "text": "알고리즘아 고맙다...",
      "likeCount": 11,
      "publishedAt": "2022-12-03T19:05:44Z"
    },
    {
      "author": "@김한울-v6j",
      "text": "26:45 그 쪽 패밀리는 다 코미디언이잖앜ㅋㅋㅋㅋㅋㅋㅋ",
      "likeCount": 6,
      "publishedAt": "2020-02-29T00:43:19Z"
    },
    {
      "author": "@전정인-m3n",
      "text": "만화가여서그런지 구체적인 상황설정이나 유발되는 에피소드를 잘만들어서 재미있어요",
      "likeCount": 12,
      "publishedAt": "2020-07-28T03:41:37Z"
    },
    {
      "author": "@마드림",
      "text": "32:51 그만해! 듣고 배아프게 웃다가 계속 돌려보니 톤이랑 앙 다물었다 떼는 입술 너무 귀여움..ㅠㅠ",
      "likeCount": 4,
      "publishedAt": "2021-11-28T18:31:25Z"
    },
    {
      "author": "@이병이병건-o2t",
      "text": "무릎꿇고 똥싸기 상상안되는데 계속 뭔가 상상됨ㅋㅋㅋㅋㅋㅋㅋㅋㅋㅋ더러워",
      "likeCount": 44,
      "publishedAt": "2020-02-28T10:58:14Z"
    },
    {
      "author": "@최달달-r8y",
      "text": "자려고 틀었다가 남장여자 예시가 매직박이래서 웃느라 잠깸 ㅅㅂㅋㅋㅋ",
      "likeCount": 1,
      "publishedAt": "2025-10-25T15:36:50Z"
    },
    {
      "author": "@lallalllaala",
      "text": "더위면역이 이긴 이유는 다들 푸짐해서 추울일 적은 사람들이 생방 보니까 그렇게 됐다 이말이야",
      "likeCount": 1,
      "publishedAt": "2023-10-29T16:35:36Z"
    },
    {
      "author": "@mygd4",
      "text": "오늘 월드컵 방장도 찐텐이고 개웃기네ㅋㅋㅋㅋ",
      "likeCount": 11,
      "publishedAt": "2020-02-28T11:17:49Z"
    },
    {
      "author": "@jjan9g",
      "text": "16:20 4 년 천보 도랐나 ㅋㅋㅋㅋㅋㅋㅋㅋ",
      "likeCount": 41,
      "publishedAt": "2020-02-28T11:50:06Z"
    },
    {
      "author": "@jungrylls7495",
      "text": "5:30\n원하는 곳으로 순간이동이 개꿀아님?\n편도면 \n집 -> A \nA -> B \nB -> 집\n이렇게 집으로 갈 수 있잖아",
      "likeCount": 2,
      "publishedAt": "2020-09-14T03:42:31Z"
    },
    {
      "author": "@muso0088",
      "text": "침마카세 최고야!",
      "likeCount": 3,
      "publishedAt": "2022-12-01T20:33:35Z"
    },
    {
      "author": "@user-dh6sk7ko3l",
      "text": "경매시키고 관찰하면서 웃는게 완전 트수잘다뤄ㅋㅋㅋㅋ",
      "likeCount": 2,
      "publishedAt": "2023-10-28T04:18:26Z"
    },
    {
      "author": "@crash4859",
      "text": "36:11 지구온난화면 겨울에 더추워짐",
      "likeCount": 1,
      "publishedAt": "2022-01-18T01:27:19Z"
    },
    {
      "author": "@user-fm2zl6px4f",
      "text": "무릎똥 진짜 개웃엇네 침마카세 ㅆㅅㅌㅊ",
      "likeCount": 11,
      "publishedAt": "2022-12-02T11:40:59Z"
    },
    {
      "author": "@user-ri1bu7xx8x",
      "text": "아... 귀한 영상을 너무 빨리 봐버렷단 말이지... 진짜 도네+침착의 조화는... 완벽.. 이랄까?..",
      "likeCount": 11,
      "publishedAt": "2020-02-28T22:28:50Z"
    },
    {
      "author": "@mp-0714",
      "text": "오마카세 맛있다",
      "likeCount": 2,
      "publishedAt": "2022-12-04T06:42:22Z"
    },
    {
      "author": "@최현태-m9l",
      "text": "2번째 거는 후자가 더 고민되는 게,\n맛만 좋으면 그만 아니냐라는 생각하고\n어차피 사귀어봐야 남자랑 다를 거 없는데 우리한테는 일반적인 데이트 아니냐라는 생각하고\n그 둘이 팽팽하게 싸움\n\n이런 생각하면서 눈물나는 내가 싫지 않은 느낌?",
      "likeCount": 1,
      "publishedAt": "2020-03-04T01:23:36Z"
    },
    {
      "author": "@kimtj-mf2yq",
      "text": "9:34 일찐맨",
      "likeCount": 6,
      "publishedAt": "2020-02-28T11:18:52Z"
    },
    {
      "author": "@calneisia",
      "text": "30:02 이슬맨",
      "likeCount": 5,
      "publishedAt": "2020-02-28T10:44:29Z"
    },
    {
      "author": "@이혜윤-f9r",
      "text": "진짜 무릎꿇고  똥싸기가 제일웃ㄱ네ㅜ진짜 ㅋㅋㅋㅋ",
      "likeCount": 3,
      "publishedAt": "2020-03-14T16:24:51Z"
    },
    {
      "author": "@최인영인영",
      "text": "진짜 미친놈처럼 웃었네 ㅋㅋㅋㅋㅋ",
      "likeCount": 25,
      "publishedAt": "2020-02-28T11:25:08Z"
    },
    {
      "author": "@짱쯔-m4x",
      "text": "침마카세야 고마워",
      "likeCount": 3,
      "publishedAt": "2022-12-04T15:23:32Z"
    },
    {
      "author": "@jae7432",
      "text": "모래마찰 진짜 논리갑이다. 이길수가 없다.",
      "likeCount": 29,
      "publishedAt": "2020-03-01T00:57:24Z"
    },
    {
      "author": "@아아아-z6l4h",
      "text": "32:45 진짜 무릎똥은 ㅈㄴ 레전드네 ㅋㅋㅋㅋ",
      "likeCount": 83,
      "publishedAt": "2022-12-04T13:56:32Z"
    },
    {
      "author": "@유삐-q5i",
      "text": "20:28 여자들한테는 완전 벨붕이에요 머리 길면 한번 감고 린스까지 하는게 너무 오래걸림ㅜㅜㅠ",
      "likeCount": 2,
      "publishedAt": "2020-06-18T12:56:52Z"
    },
    {
      "author": "@Gus3327",
      "text": "아니 집에 있는데 왜 아무도 화장실을 쓰려고 하지 않는건데",
      "likeCount": 2,
      "publishedAt": "2020-06-22T15:00:21Z"
    },
    {
      "author": "@danji3567",
      "text": "26:11 세상에서 제일 잘생긴 우리아들",
      "likeCount": 3,
      "publishedAt": "2020-02-29T05:16:32Z"
    },
    {
      "author": "@솔딕",
      "text": "순간이동은 편도라서 세계여행이 불가능합니다\n미국가면 비행기타고 한국돌아와야 다시순간이동가능\n근데 공항에서 잡힘 불법입국자임..\n그게아니면 편도가아니죠",
      "likeCount": 1,
      "publishedAt": "2022-05-04T02:22:34Z"
    },
    {
      "author": "@fedhori4407",
      "text": "42:05 인트로",
      "likeCount": 4,
      "publishedAt": "2020-02-28T10:08:47Z"
    },
    {
      "author": "@동글이-n6o",
      "text": "31:30 부터 하이라이트 ㄹㅇ개뿜었네 햇반드립 ㅋㅋㅋ",
      "likeCount": 18,
      "publishedAt": "2020-02-28T11:43:58Z"
    },
    {
      "author": "@박재동-m5r",
      "text": "x2라 사실상 32강 분량 ㄱㅇㄷ",
      "likeCount": 9,
      "publishedAt": "2020-02-28T10:11:56Z"
    },
    {
      "author": "@지혀기네",
      "text": "웃겨서 채팅창을 못보고 있어요 ㅋㅋㅋㅋㅋㅋㅋㅋㅋㅋㅋㅋㅋㅋㅋㅋㅋㅋㅋㅋ",
      "likeCount": 2,
      "publishedAt": "2020-03-01T06:24:08Z"
    },
    {
      "author": "@seonkilyu5610",
      "text": "월드컵속 월드컵이라니 \n두배로 즐겨야겠군",
      "likeCount": 1,
      "publishedAt": "2020-02-28T10:01:06Z"
    },
    {
      "author": "@Ww-pg5kk",
      "text": "침펄토론에 소재 월드컵.. 이건 귀하군요..",
      "likeCount": 2,
      "publishedAt": "2020-03-01T03:38:02Z"
    },
    {
      "author": "@A_Josh",
      "text": "1:50 여자 직박이형 vs 머리 긴 직박이형",
      "likeCount": 1,
      "publishedAt": "2021-12-30T06:08:21Z"
    },
    {
      "author": "@김햇살-v5z",
      "text": "인트로 개웃기네ㅋㅋㅋㅋㅋ",
      "likeCount": 25,
      "publishedAt": "2020-02-28T10:03:42Z"
    },
    {
      "author": "@SOSO_so823",
      "text": "밥먹으면서 보기 참 좋은 영상이네요 ^^",
      "likeCount": 0,
      "publishedAt": "2020-03-07T07:02:56Z"
    },
    {
      "author": "@october4lake",
      "text": "그 놈에 지잉~ 30:00\n오랜만에 “그마내!” 32:00",
      "likeCount": 2,
      "publishedAt": "2020-02-29T19:40:10Z"
    },
    {
      "author": "@ozz02",
      "text": "16:23 댓글에 2월 29일이면 4년 천보ㅋㅋㅋㅋㅋㅋㅋㅋㅋㅋㅋㅋㅋ",
      "likeCount": 5,
      "publishedAt": "2020-02-28T13:59:49Z"
    },
    {
      "author": "@전강민-e1l",
      "text": "10:24 뜬금 침리오",
      "likeCount": 2,
      "publishedAt": "2020-02-28T16:17:34Z"
    },
    {
      "author": "@milksoft1576",
      "text": "당연히 윤은혜 생각했는데 매직박님 생각하라는거에서 개터졌는데 ㅋㅋㅋㅋㅋㅋㅋㅋㅋㅋㅋ 가발씌운다니까 합성해서 사진첨부하는거 보고 진짜 미친듯이 웃었다 ㅋㅋㅋㅋㅋㅋㅋㅋㅋㅋㅋㅋㅋ",
      "likeCount": 11,
      "publishedAt": "2020-02-29T00:14:15Z"
    },
    {
      "author": "@moji0272",
      "text": "두피청결이죠....머리가깨끗해야 안빠질테니...",
      "likeCount": 1,
      "publishedAt": "2022-07-01T11:08:24Z"
    },
    {
      "author": "@MULKOK",
      "text": "아껴두고봐야지....ㅎㅎ",
      "likeCount": 1,
      "publishedAt": "2020-02-28T20:56:53Z"
    },
    {
      "author": "@sazaman0",
      "text": "31:31부터 ㄹㅇ 개웃기네 ㅋㅋㅋㅋㅋㅋㅋㅋ",
      "likeCount": 21,
      "publishedAt": "2020-02-29T16:39:54Z"
    },
    {
      "author": "@사람-e6u",
      "text": "황금밸런스면 채팅창이 서로 싸우고 올라가는 속도가 엄청 빠름ㅋㅋㅋ",
      "likeCount": 3,
      "publishedAt": "2020-03-02T15:54:56Z"
    },
    {
      "author": "@rehein429",
      "text": "43:39  32%대 68%면 2배넘게차이나는거임 비등비등한게아닌데",
      "likeCount": 2,
      "publishedAt": "2020-03-03T14:03:36Z"
    },
    {
      "author": "@성이름-f1r3i",
      "text": "5분 15초에 원하는곳으로 순간이동 편도가훨좋은게 굳이 가는거만 생각해야함? 갔다가 오는데 쓸수도있음 고로\n어디서든 집으로 순간이동이 원하는곳으로 순간이동 편도의 하위호환이라고 나는 생각함",
      "likeCount": 1,
      "publishedAt": "2020-02-29T12:11:32Z"
    },
    {
      "author": "@sunyou337",
      "text": "18:20 북마크",
      "likeCount": 1,
      "publishedAt": "2020-03-03T02:55:41Z"
    },
    {
      "author": "@user-em9jm1xq5n",
      "text": "2:40 갑자기 매직박형님 ㅋ ㅋ ㅋ ㅋ ㅋ ㅋ ㅋ ㅋ ㅋ ㅋ ㅋ ㅋ ㅋ ㅋ ㅋ ㅋ",
      "likeCount": 0,
      "publishedAt": "2020-02-28T15:21:56Z"
    },
    {
      "author": "@keemchichi",
      "text": "오마카세 바꿔줘잉",
      "likeCount": 3,
      "publishedAt": "2022-12-16T10:18:03Z"
    },
    {
      "author": "@fife9230",
      "text": "해수욕장 모래찜질은 겨울에눈가지고 노는거랑 똑같음",
      "likeCount": 1,
      "publishedAt": "2021-06-13T05:47:57Z"
    },
    {
      "author": "@space_return_28",
      "text": "개웃기네 진짴ㅋㅋㅋㅋㅋㅋㅋㅋㅋㅋㅋㅋㅋㅋㅋ",
      "likeCount": 16,
      "publishedAt": "2020-02-28T10:59:39Z"
    },
    {
      "author": "@이띠용-j3m",
      "text": "침착맨처럼 맛없게 먹기vs혁준이처럼 많이 먹기",
      "likeCount": 1,
      "publishedAt": "2020-02-28T10:19:37Z"
    },
    {
      "author": "@Ahrasblue",
      "text": "모래마찰좌는 기억될것입니다.",
      "likeCount": 2,
      "publishedAt": "2020-02-28T18:03:15Z"
    }
  ]
}