{
  "video_id": "syYbS4PHHyw",
  "comment_count": 3,
  "comments": [
    {
      "author": "@Olorine",
      "text": "훌룡합니다. 딴지 걸 부분이 하나도 없군요. 과연 MVP다운 플레이였습니다.",
      "likeCount": 0,
      "publishedAt": "2016-10-20T12:07:25Z"
    },
    {
      "author": "@batman_6878",
      "text": "침얍 조아~",
      "likeCount": 0,
      "publishedAt": "2020-07-12T11:09:57Z"
    },
    {
      "author": "@13367-o",
      "text": "유물 조회수 만을 안넘는 개 희귀영상",
      "likeCount": 0,
      "publishedAt": "2024-03-10T05:52:04Z"
    }
  ]
}