{
  "video_id": "udGlUzZPRqg",
  "comment_count": 11,
  "comments": [
    {
      "author": "@GranDPG",
      "text": "성기사가 못햇다 2판째.. 신병 두마리일때 평등쓰고 잡았으면 미래있었는데 그걸 또 욕심이... 솔직 한초내고 크로마구스냈으면 이겨야지 응격도 버리고..",
      "likeCount": 1,
      "publishedAt": "2017-03-20T08:49:04Z"
    },
    {
      "author": "@Jamenese",
      "text": "딱코딱뎀 확실히 배우신분",
      "likeCount": 1,
      "publishedAt": "2017-03-19T10:57:12Z"
    },
    {
      "author": "@삐깨삐갯피캐쮸-i4k",
      "text": "비취 신념을 바치게 힝힝행행홍훙훙",
      "likeCount": 0,
      "publishedAt": "2017-03-20T16:17:30Z"
    },
    {
      "author": "@이재운-o5q",
      "text": "실력겜이 또...",
      "likeCount": 0,
      "publishedAt": "2017-03-20T13:43:15Z"
    },
    {
      "author": "@내안에하늘과숲과슬기",
      "text": "침착맨 나와춤춰요 너무 찰지다ㅋㅋ",
      "likeCount": 0,
      "publishedAt": "2017-03-19T15:28:06Z"
    },
    {
      "author": "@jinus2390",
      "text": "깜놀좌표 27:32",
      "likeCount": 0,
      "publishedAt": "2017-03-24T06:12:59Z"
    },
    {
      "author": "@Kibric",
      "text": "27:10 단 하나!",
      "likeCount": 0,
      "publishedAt": "2017-03-19T10:14:17Z"
    },
    {
      "author": "@재미왕-z3u",
      "text": "속상한 이지랄맨",
      "likeCount": 0,
      "publishedAt": "2017-03-19T13:57:07Z"
    },
    {
      "author": "@유비가또",
      "text": "맬쀼리온",
      "likeCount": 0,
      "publishedAt": "2017-03-19T09:40:19Z"
    },
    {
      "author": "@러이터알",
      "text": "갸악 잼기장",
      "likeCount": 0,
      "publishedAt": "2017-03-19T08:40:54Z"
    },
    {
      "author": "@이형주-h4z",
      "text": "채팅창 우리 수장님이 하는거에 일일히 토다네 뒤지려구",
      "likeCount": 0,
      "publishedAt": "2017-03-22T03:41:31Z"
    }
  ]
}