{
  "video_id": "v08YdawuXKg",
  "comment_count": 36,
  "comments": [
    {
      "author": "@chodam199",
      "text": "27:04 매직박의 인생 분기점이 된 도네 아니냐 ㅋㅋㅋ",
      "likeCount": 56,
      "publishedAt": "2020-07-30T23:37:39Z"
    },
    {
      "author": "@jakehong8435",
      "text": "이거 나름 레전드여서 가끔 보러 들어옴 ㅋㅋㅋ",
      "likeCount": 18,
      "publishedAt": "2020-08-31T07:21:09Z"
    },
    {
      "author": "@nojamgamecrusher",
      "text": "이 편이 은근 보물이라 가끔 찾아봄",
      "likeCount": 3,
      "publishedAt": "2022-09-11T14:41:45Z"
    },
    {
      "author": "@_sam4680",
      "text": "매직박이누구에요? ㅋㅋㄱ 개웃기너 ㅋㅋㅋ",
      "likeCount": 22,
      "publishedAt": "2017-02-05T15:55:56Z"
    },
    {
      "author": "@황해정-v1t",
      "text": "대박이다ㅋㅋㅋㅋ 이렇게 연결된거였구나",
      "likeCount": 5,
      "publishedAt": "2020-10-14T15:37:55Z"
    },
    {
      "author": "@batman_6878",
      "text": "재성바래비투스 그는 여기서부터 시작했다.",
      "likeCount": 5,
      "publishedAt": "2020-11-29T12:37:47Z"
    },
    {
      "author": "@SekangKwon",
      "text": "지금의 갓보기님은 이 때에 비해서 위축된 모습인것 같아요. 이 때 모습이 더 좋아보이네요",
      "likeCount": 2,
      "publishedAt": "2020-11-06T06:44:29Z"
    },
    {
      "author": "@batman_6878",
      "text": "매직박의 화려한 데뷔",
      "likeCount": 4,
      "publishedAt": "2020-09-30T16:41:06Z"
    },
    {
      "author": "@백석봉-g4b",
      "text": "침착맨 영상을 사수하다보니 흘러흘러 여기까지 왔읍니다... 계속 즐기겠습니다. 대! 룡! *.*7",
      "likeCount": 5,
      "publishedAt": "2019-11-19T16:53:38Z"
    },
    {
      "author": "@BasicTheme",
      "text": "매직박님 너무 웃겨요ㅋㅋ",
      "likeCount": 7,
      "publishedAt": "2017-02-05T13:51:55Z"
    },
    {
      "author": "@rewrite4618",
      "text": "썸네일이 약간 마시멜로우 같은 느낌이었어요..",
      "likeCount": 10,
      "publishedAt": "2017-02-05T12:05:58Z"
    },
    {
      "author": "@사주임-b8n",
      "text": "매직박님 첨보는데 입담 엄청나시네",
      "likeCount": 7,
      "publishedAt": "2017-02-10T05:32:57Z"
    },
    {
      "author": "@mlo-s3q",
      "text": "지독한 갓보기님....",
      "likeCount": 12,
      "publishedAt": "2017-02-05T14:37:25Z"
    },
    {
      "author": "@ddd-ne1yx",
      "text": "히오스 갓겜",
      "likeCount": 5,
      "publishedAt": "2017-02-05T10:02:27Z"
    },
    {
      "author": "@내가왜이러지",
      "text": "그때 그시절 그맛...",
      "likeCount": 1,
      "publishedAt": "2022-12-21T11:03:40Z"
    },
    {
      "author": "@ecus9665",
      "text": "그랜드 브론즈의 시작",
      "likeCount": 9,
      "publishedAt": "2017-02-17T09:37:18Z"
    },
    {
      "author": "@seyangpark620",
      "text": "그립읍니다",
      "likeCount": 1,
      "publishedAt": "2022-11-21T15:40:01Z"
    },
    {
      "author": "@calmdowmman841",
      "text": "진짜 이때 개잘생겼다 ㅋㅋ",
      "likeCount": 2,
      "publishedAt": "2020-02-07T22:31:51Z"
    },
    {
      "author": "@docple11",
      "text": "매직박님 진짜 개웃기네 ㅋㅋㅋㅋㅋㅋㅋㅋ",
      "likeCount": 2,
      "publishedAt": "2017-08-03T11:17:14Z"
    },
    {
      "author": "@jiyongshin6279",
      "text": "매직박도 매직박인데 이때의 갓보기는 나쁜 의미로 미친놈이었구나",
      "likeCount": 0,
      "publishedAt": "2022-01-27T03:52:33Z"
    },
    {
      "author": "@wjdgnswkdry6245",
      "text": "배도라지의 기원",
      "likeCount": 1,
      "publishedAt": "2020-07-05T03:57:51Z"
    },
    {
      "author": "@tenmp",
      "text": "전설의 시작...",
      "likeCount": 0,
      "publishedAt": "2020-06-12T12:10:28Z"
    },
    {
      "author": "@이-x8b4b",
      "text": "매직박 ㄹㅇ 개웃기다 ㅋㅋㅋㅋㅋㅋㅋㅋㅋㅋ",
      "likeCount": 0,
      "publishedAt": "2020-05-20T16:59:51Z"
    },
    {
      "author": "@물장난감",
      "text": "2025?",
      "likeCount": 1,
      "publishedAt": "2025-01-22T01:50:14Z"
    },
    {
      "author": "@digidigimonmon",
      "text": "옥냥님 있는곳 어디든 간다!",
      "likeCount": 0,
      "publishedAt": "2018-07-19T14:52:00Z"
    },
    {
      "author": "@bittersweet0578",
      "text": "히오스가 새로나온 카카오 핸드폰게임인가요",
      "likeCount": 6,
      "publishedAt": "2017-02-05T12:35:30Z"
    },
    {
      "author": "@w_oouu99",
      "text": "매직박 : 더비기닝",
      "likeCount": 0,
      "publishedAt": "2020-09-27T05:47:16Z"
    },
    {
      "author": "@redhive0502able",
      "text": "시밬ㅋㅋㅋㅋㅋㅋㅋㅋㅋㅋㅋㅋㅋㅋㅋㅋㅋㅋㅋㅋ와 역대급 웃김ㅋㅋㅋㅋㅋㅋㅋㅋㅋㅋㅋㅋ",
      "likeCount": 1,
      "publishedAt": "2017-02-25T14:12:51Z"
    },
    {
      "author": "@dmldms34",
      "text": "간보기 ㅋㅋㅋㅋㅋ",
      "likeCount": 0,
      "publishedAt": "2017-02-05T13:09:06Z"
    },
    {
      "author": "@이-x8b4b",
      "text": "갓보기 ㅋㅋㅋㅋㅋㅋㅋㅋㅋㅋ 뺄게요",
      "likeCount": 0,
      "publishedAt": "2020-05-20T17:08:43Z"
    },
    {
      "author": "@김매인",
      "text": "47:48 뻐기어빠 마이크 20세기에서 무전치는건가요?",
      "likeCount": 2,
      "publishedAt": "2020-07-19T02:37:04Z"
    },
    {
      "author": "@user-ds4qj7cq2w",
      "text": "이게 바로 배도라지 매직박의 합류..?! 전설이다..",
      "likeCount": 0,
      "publishedAt": "2020-11-01T11:48:48Z"
    },
    {
      "author": "@yuzatea",
      "text": "면접시작은 12분 부터",
      "likeCount": 0,
      "publishedAt": "2017-02-07T00:05:05Z"
    },
    {
      "author": "@류영재-u7p",
      "text": "아조씨 아프지마세요",
      "likeCount": 0,
      "publishedAt": "2017-02-06T01:29:08Z"
    },
    {
      "author": "@liliiililii",
      "text": "이땐 진짜 하꼬긴 했네ㅋㅋㅋ 5년전 영상인데 댓글이 40개",
      "likeCount": 0,
      "publishedAt": "2023-01-03T16:28:11Z"
    },
    {
      "author": "@앙로드호구띠",
      "text": "각오 한마디 어디갔어 ㅠㅠㅠㅠ",
      "likeCount": 0,
      "publishedAt": "2017-02-05T20:26:46Z"
    }
  ]
}