{
  "video_id": "YqUBeniadKM",
  "comment_count": 100,
  "comments": [
    {
      "author": "@한재훈-q1u",
      "text": "아저씨들끼리 부끄러워하고 어색해하는게 왜케 귀엽냐 ㅋㅋㅋㅋㅋㅋㅋㅋ",
      "likeCount": 2793,
      "publishedAt": "2022-11-19T10:15:53Z"
    },
    {
      "author": "@frozendogs2098",
      "text": "안친한 사람 말걸 때 저는 늘 공통적인 얘기로 시작해요. 날씨가 제일 좋은 주제인데 렙틸리언 아니면 대부분 공감해줘서 시작하기 좋아요.",
      "likeCount": 134,
      "publishedAt": "2022-11-19T12:13:37Z"
    },
    {
      "author": "@koubong",
      "text": "16:30침착맨 렉걸리면서 들어오는거 웃기네 ㅋㅋㅋ",
      "likeCount": 182,
      "publishedAt": "2022-11-19T11:33:59Z"
    },
    {
      "author": "@friedchicken3546",
      "text": "7:00 말들어보니깐 침착맨 찐서윗남이네… 친구 성격 캐치해서 자기가 필두로 한거였어.. 나라면 진짜감동받음ㅠㅠ",
      "likeCount": 205,
      "publishedAt": "2022-11-19T13:57:41Z"
    },
    {
      "author": "@xlsjdjsj",
      "text": "직박이형과 서로 낯가리는 거 너무 웃김 ㅋㅋㅋㅋㅋ",
      "likeCount": 881,
      "publishedAt": "2022-11-19T10:27:21Z"
    },
    {
      "author": "@HeojaeBBALheojae",
      "text": "웃기려고 한두 명 정도 반대할 줄 알았는데 가볍게 만장일치 반대ㅋㅋㅋㅋㅋㅋㅋㅋㅋㅋㅋㅋㅋㅋㅋㅋ",
      "likeCount": 827,
      "publishedAt": "2022-11-19T10:29:18Z"
    },
    {
      "author": "@user-xj1wb6rb6z",
      "text": "풍전무님 진짜 지독한 인싸넼ㅋㅋㅋㅋㅋㅋㅋㅋㅋ 모임자리에 처음 간 사람이 폭주하면서 기존 인원들 다 말 놓게하곸ㅋㅋㅋㅋㅋ",
      "likeCount": 92,
      "publishedAt": "2022-11-22T02:44:55Z"
    },
    {
      "author": "@12121_off",
      "text": "승빠가 전무님 원래 되게 낯가리시는데 저땐 모임 분위기 맞추느라고 엄청 방송처럼 하고 계시다고ㅋㅋㅋ 진짜 프로라고 그러던덱ㅋㅋㅋㅋ\n침투부나 방송에서 전무님 오래 봐온 사람으로서 인싸 그자체! 가 아니라 엄청 노력중이신게 눈에 보임.... ㅋㅋㅋㅋ",
      "likeCount": 1575,
      "publishedAt": "2022-11-19T10:59:38Z"
    },
    {
      "author": "@moony8026",
      "text": "방장 가죽자켓 너무 존잘이다... 핸드폰 귀에 대고 있는 모습보고 화보인줄 알았어.",
      "likeCount": 35,
      "publishedAt": "2022-11-19T13:20:25Z"
    },
    {
      "author": "@DinosaurJr.",
      "text": "그나마 풍전무님이 제일 인싸라는게 학계의 정설..",
      "likeCount": 3708,
      "publishedAt": "2022-11-19T10:01:07Z"
    },
    {
      "author": "@calmdowmman841",
      "text": "동갑내기 과외하기는 사실\n직박풍커플보다 기열펄커플이 진짜 개꿀잼일듯 ㅋㅋ",
      "likeCount": 262,
      "publishedAt": "2022-11-19T11:12:53Z"
    },
    {
      "author": "@dukku46",
      "text": "전무님 스스로 본인 팝업유튜버라고 소개하시는거 너무 웃기다ㅋㅋㅋ",
      "likeCount": 1140,
      "publishedAt": "2022-11-19T11:23:24Z"
    },
    {
      "author": "@강승구-c3o",
      "text": "졸지에 떠들썩해질 뀰이 돌잔치 기대되네요",
      "likeCount": 1137,
      "publishedAt": "2022-11-19T10:04:22Z"
    },
    {
      "author": "@ceruleanblue2087",
      "text": "내향적이라는 게 혼자 있는 시간이 충전 시간이고 남들과 있을 때 그 에너지를 쓰는 거라면 풍님은 배터리 용량이 그냥 엄청 엄청 큰 걸 수도",
      "likeCount": 1228,
      "publishedAt": "2022-11-19T10:17:14Z"
    },
    {
      "author": "@ingosmind",
      "text": "5:22 아니...착맨씨 가죽자켓입고 저러고 있으니 개존잘 왜케 잘어울려...머리까지 예쁘고",
      "likeCount": 315,
      "publishedAt": "2022-11-20T00:15:58Z"
    },
    {
      "author": "@Cheese_Chicken",
      "text": "아저씨들 말 놓는 과정이 너무 귀엽네.....",
      "likeCount": 424,
      "publishedAt": "2022-11-19T10:07:41Z"
    },
    {
      "author": "@서르마-i8v",
      "text": "5:21 보다가 깜짝놀랐음.. 침착맨 옆모습 비주얼 실화냐? 아이돌이라고 해도 믿겠다",
      "likeCount": 515,
      "publishedAt": "2022-11-19T10:37:07Z"
    },
    {
      "author": "@lulululu99996",
      "text": "풍전무님 금방 적응하시는거 같아 ㅋㅋ 역시 인싸",
      "likeCount": 377,
      "publishedAt": "2022-11-19T10:23:11Z"
    },
    {
      "author": "@고기만두김치만두-j5l",
      "text": "개착맨 \n직박이형이랑 풍이형 어색하게 인사시키고 \n엄청 웃으면서 좋아하는거봐 ㅋㅋㅋㅋㅋㅋㅋㅋㅋㅋㅋㅋㅋㅋㅋㅋㅋㅋㅋㅋㅋㅋㅋㅋㅋ",
      "likeCount": 25,
      "publishedAt": "2022-11-25T21:30:23Z"
    },
    {
      "author": "@greenwood2478",
      "text": "5:22 전화거는 모습 너무 멋있어",
      "likeCount": 28,
      "publishedAt": "2022-11-19T12:55:56Z"
    },
    {
      "author": "@어부지리-g2i",
      "text": "5:25 침저씨 가죽자켓 소화력 ㄷ ㄷ \n역시 빈폴 공식 마델이다",
      "likeCount": 59,
      "publishedAt": "2022-11-19T10:44:33Z"
    },
    {
      "author": "@meehee",
      "text": "1:33 형님들 어색함에 같이 부끄러워하는 월량이형 귀여워ㅋㅋㅋ",
      "likeCount": 195,
      "publishedAt": "2022-11-19T11:54:10Z"
    },
    {
      "author": "@sisam_J",
      "text": "풀방송 봤지만 1분전은 못 참지 ㅋㅋㅋㅋ\n풍전무님의 멘트는 나이들수록 공감이 많이 됨\n나이들수록 사회생활이란 걸 점점 느끼고 필요성을 느끼고, 구분하게 되니깐 ㅋㅋㅋㅋㅋ",
      "likeCount": 873,
      "publishedAt": "2022-11-19T10:03:43Z"
    },
    {
      "author": "@숭지-j5r",
      "text": "와 이때가 직박님이랑 풍님 처음 만난때네 ㅋㅋㅋㅋㅋㅋ 영상 떴을때 보긴 했지만 라꼰에서 케미 터지는거 여러번 본후로 보니까 새삼스럽다",
      "likeCount": 4,
      "publishedAt": "2025-02-02T15:33:26Z"
    },
    {
      "author": "@DaisyP_998",
      "text": "2:21\n첫째세요?\n네 제가 첫째\n이거 진짜 미친거갘음 ㅋㅋㅋㅋㅋ",
      "likeCount": 12,
      "publishedAt": "2022-11-22T04:16:48Z"
    },
    {
      "author": "@aaaaaa-f5w",
      "text": "만장일치 반대 ㅋㅋㅋㅋㅋㅋㅋㅋㅋㅋㅋㅋㅋㅋㅋㅋㅋㅋㅋㅋㅋ",
      "likeCount": 26,
      "publishedAt": "2022-12-01T15:14:53Z"
    },
    {
      "author": "@마따따비가루",
      "text": "와 풍전무님 ㄹㅇ 생활꿀팁 돌았따.. 친화력 돌았따..",
      "likeCount": 184,
      "publishedAt": "2022-11-19T10:34:13Z"
    },
    {
      "author": "@DK-cd2tm",
      "text": "아니 분명 따로따로 구독하고 시청하던 아죠씨들인데.. 점점 세계관이 커지면서 만나고있어..........대통합ㅋㅋㅋㅋㅋㅋㅋㅋ",
      "likeCount": 305,
      "publishedAt": "2022-11-19T12:33:08Z"
    },
    {
      "author": "@chatty_sol",
      "text": "역시 팝업유튜버.. \n예전에 카페 하실 때 한번 찾아갔을 때 호방하게 웃으며 메뉴를 추천해주신 그 미소..\n오늘따라 상수의 그 카페가 생각납니다..!",
      "likeCount": 219,
      "publishedAt": "2022-11-19T10:07:38Z"
    },
    {
      "author": "@Gabriela-hq6qy",
      "text": "8:32 이것때문에 설움에 받쳐서 파김치갱 만든 거구나",
      "likeCount": 8,
      "publishedAt": "2024-10-21T01:28:44Z"
    },
    {
      "author": "@공리나",
      "text": "ㅋㅋㅋㅋ배도라지에 풍전무님이 온게 아니라 풍전무님한테 배도라지가 왔다는 말이 딱맞음",
      "likeCount": 48,
      "publishedAt": "2022-11-19T10:13:55Z"
    },
    {
      "author": "@rayofday5546",
      "text": "다들 개인방송에 쉐프 개그맨 등 카메라 앞에 서는 사람들마저 저렇게 어색해하고 낯가린다는 게 신기하네ㅋㅋㅋ",
      "likeCount": 35,
      "publishedAt": "2022-11-19T10:53:35Z"
    },
    {
      "author": "@potatostew4775",
      "text": "1:38 여기부터 서로 앉을라다가 옆에서 한마디씩 할때마다 못앉고 다시 일어나는거 개웃기네 ㅋㅋㅋㅋㅋㅋㅋㅋㅋㅋㅋ",
      "likeCount": 255,
      "publishedAt": "2022-11-19T10:23:51Z"
    },
    {
      "author": "@이거실탄이거든",
      "text": "침착맨 저기서 젤 존잘인거 보소..",
      "likeCount": 35,
      "publishedAt": "2022-11-19T11:27:56Z"
    },
    {
      "author": "@Data-designer",
      "text": "배도라지 행님들, 우리 착하고 슬픈눈을 가진 김풍전문님 잘부탁드립니다",
      "likeCount": 202,
      "publishedAt": "2022-11-19T10:02:26Z"
    },
    {
      "author": "@kimsanai5060",
      "text": "ㅋㅋㅋㅋㅋㅋㅋㅋㅋㅋㅋㅋㅋㅋㅋㅋㅋㅋㅋㅋㅋㅋㅋㅋㅋㅋㅋㅋㅋㅋㅋㅋㅋㅋㅋㅋㅋㅋㅋㅋㅋㅋㅋㅋㅋㅋㅋㅋㅋㅋㅋㅋㅋㅋㅋ 아 풍형 앉앗다가 일어나고 앉앗다가 일어나고 못앉는거 개웃기넼ㅋㅋㅋㅋㅋ",
      "likeCount": 86,
      "publishedAt": "2022-11-19T10:04:00Z"
    },
    {
      "author": "@Maagneeto",
      "text": "다나카도 품어주시는 전무님인 데\n한국인하고 친해지는 건 껌이지 ㅋㅋㅋㅋㅋ",
      "likeCount": 48,
      "publishedAt": "2022-11-19T10:24:41Z"
    },
    {
      "author": "@포슬포슬",
      "text": "방장이 희민이도 이런식으로 주펄 집에 데려갔을 거 생각하니....ㅋㅋㅋㅋㅋㅋㅋㅋ",
      "likeCount": 40,
      "publishedAt": "2022-11-19T12:27:45Z"
    },
    {
      "author": "@user-single2ya",
      "text": "다른걸 떠나서 저렇게 재밌게 놀수있는 잘 맞는 친구들이 있다는게 너무 부럽다 ㅎ",
      "likeCount": 55,
      "publishedAt": "2022-11-19T16:13:49Z"
    },
    {
      "author": "@polypolyweb",
      "text": "이분은 갈수록 호감형이야. 살찐걸로 안보이고 풍채라는말이 절로 나와",
      "likeCount": 103,
      "publishedAt": "2022-11-19T10:27:58Z"
    },
    {
      "author": "@potatostew4775",
      "text": "5:05 기열킹 어색한 분위기에 몸서리치는거봐 ㅋㅋㅋㅋㅋㅋㅋ",
      "likeCount": 43,
      "publishedAt": "2022-11-19T10:27:47Z"
    },
    {
      "author": "@muffinm",
      "text": "5:11 존잘맨 미쳤다;;",
      "likeCount": 13,
      "publishedAt": "2022-11-19T17:52:23Z"
    },
    {
      "author": "@timpark8918",
      "text": "나는 침튜브에서 김풍님 너무 오래봐서 이 풀방송 너무 조마조마하게 봄.. 진짜 인팁이 모든 능력을 초월해서 사회성을 발휘한 방송이었음.. 방송이니까 노력하는게 눈에 보였다랄까..",
      "likeCount": 151,
      "publishedAt": "2022-11-19T15:46:38Z"
    },
    {
      "author": "@이재영-h2m",
      "text": "2:20 깔깔유머에서나 나올 기적의 만담 ㅋㅋㅋㅋㅋㅋㅋㅋㅋㅋㅋ",
      "likeCount": 15,
      "publishedAt": "2022-11-19T10:07:05Z"
    },
    {
      "author": "@PoTpoo",
      "text": "이런 식으로 기안도 주펄 집에 데려갔나 ㅋㅋㅋㅋㅋㅋㅋ\n집주인은 아무 말도 없는데 침착맨이 상관없어 같이 가자 ㅋㅋㅋㅋㅋㅋ",
      "likeCount": 30,
      "publishedAt": "2022-11-19T10:16:39Z"
    },
    {
      "author": "@뀨뀨까까-h6s",
      "text": "5:21 넘 잘생겨서보다가 놀랐…!",
      "likeCount": 7,
      "publishedAt": "2024-02-22T10:15:47Z"
    },
    {
      "author": "@yuk7852",
      "text": "풍 형을 처음 본 사람은 싫어할 수도 있다. 그런데 계속 보면 시기의 문제이지ㅋㅋㅋ결국엔 좋아할 수밖에 없다. 난 아직도 기끔 감탄하면서 봄ㅋㅋㅋ 저봐 풍월량님네 가서 형사 썰 나오는거 봐ㅋㅋㅋㅋ 어케 이야기 보따리가 마르지를 않아?",
      "likeCount": 157,
      "publishedAt": "2022-11-19T17:12:04Z"
    },
    {
      "author": "@StingTV",
      "text": "언제 한번 스튜디오에서 동갑 커플 게임하면서 친해질길 바래 했으면 좋겠습니다. ㅋㅋㅋㅋㅋㅋㅋㅋ",
      "likeCount": 537,
      "publishedAt": "2022-11-19T10:11:40Z"
    },
    {
      "author": "@ranmahalf-q3w",
      "text": "05:22 존잘맨;;",
      "likeCount": 14,
      "publishedAt": "2022-11-19T10:16:51Z"
    },
    {
      "author": "@가나-m9x5g",
      "text": "아 개웃기네 ㅋㅋㅋ 진짜 근데 적응력왜케좋은거야 풍전무님은",
      "likeCount": 68,
      "publishedAt": "2022-11-19T10:06:29Z"
    },
    {
      "author": "@user-pk9cw7wb4r",
      "text": "역시 말을 신박하게 잘하는 두사람이니 든든하네",
      "likeCount": 44,
      "publishedAt": "2022-11-19T10:05:36Z"
    },
    {
      "author": "@세원기",
      "text": "다 알고 나만 모르는 사이 저거 진짜 힘든건데 ㅋㅋ",
      "likeCount": 14,
      "publishedAt": "2022-11-19T13:14:09Z"
    },
    {
      "author": "@16752",
      "text": "어른되서 저렇게 결이 비슷한 사람들 만나서 친해지기 어려운데. 방장이 좋은사람이니 좋은사람들만 모이는구나",
      "likeCount": 5,
      "publishedAt": "2022-11-19T14:28:47Z"
    },
    {
      "author": "@My_Dragon",
      "text": "병거니우스의 모험 할 적에 재성바래비투스 보고 풍 횐님이 자꾸 재성이가라고 하니까 그..실존인물이라서요..라고 했던게 엊그제 같은데 진짜 만나서 배도라지 얘기하고 계시네 ㅋㅋㅋㅋㅋㅋㅋ",
      "likeCount": 39,
      "publishedAt": "2022-11-20T09:09:34Z"
    },
    {
      "author": "@hynj9100",
      "text": "침착맨이 젤 인싸아님?\n초면인 주호민 작가님한테 대뜸 전화해서 1시간 통화하고 안친한데 반려기안84까지 데꼬가서 밥 먹였잖슴ㅋㅋㅋㅋㅋㅋ",
      "likeCount": 67,
      "publishedAt": "2022-11-19T10:11:26Z"
    },
    {
      "author": "@재명이-f4d",
      "text": "저 첫째드립은 볼때마다 개웃기다ㅋㅋㄱㅋ",
      "likeCount": 13,
      "publishedAt": "2022-11-19T11:30:54Z"
    },
    {
      "author": "@jinwoo005",
      "text": "5:20 침착맨 가죽자켓입고 통화하는 옆모습 미쳤네ㄷㄷ",
      "likeCount": 28,
      "publishedAt": "2022-11-19T13:45:49Z"
    },
    {
      "author": "@lllllllll-m8m",
      "text": "0:42 풍님이랑 풍월량님이랑 폰에 서로번호저장되어있는게 넘 웃겼어요ㅋㅋ",
      "likeCount": 4,
      "publishedAt": "2023-05-26T12:06:55Z"
    },
    {
      "author": "@KIMKIM-wo5nz",
      "text": "침착맨 가죽자켓 입었네...왜 점점 더 잘 생겨지냐?ㅋㅋㅋ",
      "likeCount": 9,
      "publishedAt": "2022-11-19T12:39:38Z"
    },
    {
      "author": "@dPE30",
      "text": "5:23 쌉존잘맨 ;",
      "likeCount": 9,
      "publishedAt": "2022-11-19T14:23:43Z"
    },
    {
      "author": "@chunoggun",
      "text": "1:41 기열킹ㅋㅋㅋ 둘을 슥 보더니 카메라 찾아서 \"봤지?\" ㅋㅋㅋㅋㅋㅋㅋㅋ",
      "likeCount": 4,
      "publishedAt": "2022-11-19T12:06:01Z"
    },
    {
      "author": "@OASNDWQD",
      "text": "침착맨 존잘이네 말없으니까",
      "likeCount": 10,
      "publishedAt": "2022-11-19T14:50:38Z"
    },
    {
      "author": "@allofpassion",
      "text": "풍전무님 진짜 조직론 논문한편 쓰셔야겠네 너무 잘하신다",
      "likeCount": 11,
      "publishedAt": "2022-11-29T17:30:02Z"
    },
    {
      "author": "@user-AHAHA20",
      "text": "내향적인게 사람마다 다 다르긴 한거같음 어떤사람은 집에만 있는거 좋아하는데 막상 자리에 부르면 잘놀고 다음자리까지 쿨타임이 있고 어떤사람은 아예 자리 나가는걸 거북해하고",
      "likeCount": 5,
      "publishedAt": "2022-11-19T10:34:00Z"
    },
    {
      "author": "@RuKo-e9z",
      "text": "아 진짜 보면서 너무 행복하고 재밌었음ㅋㅋㅋㅋㅋ",
      "likeCount": 22,
      "publishedAt": "2022-11-19T11:04:43Z"
    },
    {
      "author": "@movieking741",
      "text": "내 이랄줄 알앗다 풍님 실제로 봣을때 얼굴에서 빛이 나는게 광택메이컵을 햇나햇는데 인싸력 오오라엿구나",
      "likeCount": 16,
      "publishedAt": "2022-11-19T10:46:10Z"
    },
    {
      "author": "@Chiwoneee",
      "text": "중간에 좀 잘생긴 아저씨네 했는데 김기열이네 개그맨이 젤 조용한게 개웃김 ㅋㅋ",
      "likeCount": 6,
      "publishedAt": "2022-11-19T10:50:48Z"
    },
    {
      "author": "@everyletterisentyou",
      "text": "5:15 존잘맨",
      "likeCount": 7,
      "publishedAt": "2022-11-19T10:14:41Z"
    },
    {
      "author": "@hayley4977",
      "text": "5:22 무친 존잘맨......이거 맞아? 아니 너무 잘생김",
      "likeCount": 6,
      "publishedAt": "2022-11-19T16:03:13Z"
    },
    {
      "author": "@빵ye애yo",
      "text": "항상 썸네일은 어떻게 이렇게 개웃기게 만드냐 진짜 ㅋㅋㅋㅋㅋㅋㅋㅋㅋ",
      "likeCount": 28,
      "publishedAt": "2022-11-19T14:06:13Z"
    },
    {
      "author": "@PiccoloBro",
      "text": "나도 풍형 같은 방식으로 먼저 유하게 말놓아서 편해지게 하려고 하는데\n어떤사람들한테는 그게 되게 예의없게 비춰지나보더라.. \n내친구가 저런 비슷한 상황에서 앞에서는 허허 웃으면서 넘어가고서 뒤에서 험담 엄청해서 놀랏음\n(그때는 다른사람이 내 친구에게 말놓은 상황)",
      "likeCount": 6,
      "publishedAt": "2022-11-19T15:09:52Z"
    },
    {
      "author": "@iiIIiIiIiIIii-y5r",
      "text": "30~40대 아조씨들 왜이렇게 건전하게 노냐ㅋㅋㅋㅋㅋ보기좋",
      "likeCount": 39,
      "publishedAt": "2022-11-19T11:00:48Z"
    },
    {
      "author": "@calm.down.man.",
      "text": "진짜 씹인싸풍이다ㅋㅋㅋㅋㅋㅋㅋㅋ",
      "likeCount": 13,
      "publishedAt": "2022-11-19T10:23:58Z"
    },
    {
      "author": "@냥냥펀치-w6z",
      "text": "월량이형 집들이를 보면 고길동의 심정을 알 수 있습니다",
      "likeCount": 65,
      "publishedAt": "2022-11-19T10:08:06Z"
    },
    {
      "author": "@bleckbleckbleck",
      "text": "4:26 차돌짬뽕 순식간에 예의없는 사람행ㅋㅋㅋㅋㅋ",
      "likeCount": 3,
      "publishedAt": "2022-11-20T08:10:22Z"
    },
    {
      "author": "@fourstone771",
      "text": "그 와중에 개방장 왤케 잘생김??? 킹받네",
      "likeCount": 24,
      "publishedAt": "2022-11-19T10:18:16Z"
    },
    {
      "author": "@rorodesu",
      "text": "5:24 존잘맨 ㄷㄷ",
      "likeCount": 4,
      "publishedAt": "2022-11-25T20:20:59Z"
    },
    {
      "author": "@민동준-o1r",
      "text": "침착맨 주우재가 선물한 가죽자켓 잘 입고 다니네 ㅋㅋㅋㅋㅋ 방송에서 한 말이 아니라 진짜 맘에 들었나봐",
      "likeCount": 19,
      "publishedAt": "2022-11-19T17:18:45Z"
    },
    {
      "author": "@띵-y9l",
      "text": "5:23 전화 거는 옆태 에반데",
      "likeCount": 4,
      "publishedAt": "2022-11-20T03:52:04Z"
    },
    {
      "author": "@jjinooasmr",
      "text": "다 같이 모여서 노는 모습 너무 좋아보여요😆",
      "likeCount": 6,
      "publishedAt": "2022-11-29T07:36:14Z"
    },
    {
      "author": "@소가위",
      "text": "아니 저 여러명 모인자리에서 술도 안먹고 저 텐션 나온다는게 ㅋㅋㅋㅋ",
      "likeCount": 11,
      "publishedAt": "2022-11-19T10:27:20Z"
    },
    {
      "author": "@농대너구리",
      "text": "가짜아싸 전무님 풍 미쳤다",
      "likeCount": 17,
      "publishedAt": "2022-11-19T10:02:54Z"
    },
    {
      "author": "@CHETID",
      "text": "16:30 개방장 잔망과 번잡 사이",
      "likeCount": 8,
      "publishedAt": "2022-11-19T12:41:00Z"
    },
    {
      "author": "@potatostew4775",
      "text": "인트로 71-10 뭔가했더니 기-열 ㅋㅋㅋㅋㅋㅋㅋㅋㅋㅋㅋㅋㅋ",
      "likeCount": 12,
      "publishedAt": "2022-11-19T10:21:44Z"
    },
    {
      "author": "@jwl1260",
      "text": "치과의사.....\n이것저것 팝업유투버.....\n개웃기내ㅋㅋ",
      "likeCount": 10,
      "publishedAt": "2022-11-19T10:14:22Z"
    },
    {
      "author": "@차또르키짱",
      "text": "5:25 통화할 때부터 의식했는데 겁나 잘생겼네ㄸ",
      "likeCount": 8,
      "publishedAt": "2022-11-19T12:38:39Z"
    },
    {
      "author": "@스트렝스기록용",
      "text": "저는 친하다고 무조건 말 놓고 하는건 반대합니다\n나이를 먹고보니 아주 가깝고 친한친구에게도\n조심하고 존중하게 되는 시점이라 그런지\n존댓말로도 충분히 재밌고 가깝게 지낼수있다고 생각합니다\n서로 존댓말 하면서 사는 부부들이 최소한 욕설은 안하는거처럼\n할말 다하되 선은 지킬수있게 되는거 같습니다",
      "likeCount": 16,
      "publishedAt": "2022-11-19T10:48:57Z"
    },
    {
      "author": "@Cloudland0809",
      "text": "배도라지는 매직박 형이 웃기고 탱커하고 다 해줘서 더 잘굴러감",
      "likeCount": 5,
      "publishedAt": "2022-11-19T11:27:14Z"
    },
    {
      "author": "@stormi.",
      "text": "이거 풀버젼꼭봐야됨 \n진짜 너무 시끄러운데 너무 재밌음",
      "likeCount": 44,
      "publishedAt": "2022-11-19T10:08:24Z"
    },
    {
      "author": "@hsb9904",
      "text": "이거 본 내년 신입생 중에 몇명은 선배나 재수생한테 실수해서 분위기 박살낼듯ㅋㅋㅋㅋㅋㅋㅋ",
      "likeCount": 21,
      "publishedAt": "2022-11-19T10:41:18Z"
    },
    {
      "author": "@ajax1194",
      "text": "3:01 기백 있어 ㅋㅋㅋㅋㅋㅋ",
      "likeCount": 5,
      "publishedAt": "2022-11-19T10:48:50Z"
    },
    {
      "author": "@chichacachocho4167",
      "text": "풍도라지 너무 재밌네요 ㅋㅋㅋㅋ",
      "likeCount": 7,
      "publishedAt": "2022-12-01T00:20:49Z"
    },
    {
      "author": "@너구링-d8c",
      "text": "5:26 ㄷ ㄷ 침착맨 개잘생김 \n처음에 박정민인줄 알고 '배우가 다르긴하네..'라고 생각하고 있었는데 침착맨이었슴;",
      "likeCount": 4,
      "publishedAt": "2022-11-19T13:10:08Z"
    },
    {
      "author": "@Ruliling",
      "text": "이제는 낯가릴 시간도 없지. 앞으로 만날사람과 안볼사람 구분해서 만날사람만 신경쓰면됨",
      "likeCount": 2,
      "publishedAt": "2022-11-20T05:16:35Z"
    },
    {
      "author": "@phasor8349",
      "text": "8:38 만장일치 ㅋㅋㅋㅋㅋㅋㅋㅋㅋ",
      "likeCount": 9,
      "publishedAt": "2022-11-19T10:09:16Z"
    },
    {
      "author": "@장칼국수-d1u",
      "text": "아니 요새 왜이렇게 존잘맨....? 왜이래 요즘",
      "likeCount": 8,
      "publishedAt": "2022-11-19T10:06:38Z"
    },
    {
      "author": "@justitia5794",
      "text": "아니 술자리에서 승빠님 무게감 장난아니시네 ㄷㄷ\n요리사 포스인가?",
      "likeCount": 23,
      "publishedAt": "2022-11-19T13:04:43Z"
    },
    {
      "author": "@gam_messi",
      "text": "22:19 억까인데 펄형 타격감이 참 좋고 잘받아줘ㅋㅋㅋㅋㅋㅋㅋㅋㅋㅋㅋㅋㅋ\n주미륵 덕분에 잘웃었습니다",
      "likeCount": 10,
      "publishedAt": "2022-11-25T15:46:03Z"
    },
    {
      "author": "@parkuku",
      "text": "16:30 초인싸등장",
      "likeCount": 7,
      "publishedAt": "2022-11-19T10:43:58Z"
    },
    {
      "author": "@Gooninguntildie",
      "text": "나 이장면 라이브로 봣엇는데 솔직히 다같이 말하니까 무슨말인지 이해안된거많앗어서 자막보고 이제 제대로 보게됨ㅋㅋ",
      "likeCount": 6,
      "publishedAt": "2022-11-19T10:07:33Z"
    }
  ]
}